django_kck/__init__.py
django_kck/apps.py
django_kck/cache.py
django_kck/exceptions.py
django_kck/factories.py
django_kck/hints.py
django_kck/hooks.py
django_kck/models.py
django_kck/parameters.py
django_kck/primer.py
django_kck/process.py
django_kck/test.py
django_kck/migrations/0001_initial.py
django_kck/migrations/0002_auto_20190927_0515.py
django_kck/migrations/__init__.py
django_kck-0.0.56.data/data/README.md
django_kck-0.0.56.dist-info/LICENSE.md
django_kck-0.0.56.dist-info/METADATA
django_kck-0.0.56.dist-info/WHEEL
django_kck-0.0.56.dist-info/entry_points.txt
django_kck-0.0.56.dist-info/top_level.txt
django_kck-0.0.56.dist-info/RECORD
