Metadata-Version: 2.1
Name: django-kck
Version: 0.0.56
Summary: Data orchestration for Django
Home-page: https://gitlab.com/frameworklabs/django-kck
Author: Framework Labs
Author-email: fred@frameworklabs.us
License: BSD
Keywords: data orchestration framework
Platform: UNKNOWN
Classifier: Development Status :: 2 - Pre-Alpha
Classifier: Intended Audience :: Developers
Classifier: Topic :: Software Development :: Libraries :: Python Modules
Classifier: Framework :: Django
Classifier: License :: OSI Approved :: BSD License
Classifier: Programming Language :: Python :: 3.6
Requires-Dist: Django (>=2.0.0)
Requires-Dist: python-dateutil (>=2.2)
Requires-Dist: django-postgres-extensions (>=0.9.3)
Requires-Dist: psycopg2-binary (>=2.7.6.1)
Requires-Dist: django-picklefield (==2.0)
